django_json_schema_model/__init__.py
django_json_schema_model/admin.py
django_json_schema_model/apps.py
django_json_schema_model/models.py
django_json_schema_model/py.typed
django_json_schema_model/locale/nl/LC_MESSAGES/django.po
django_json_schema_model/migrations/0001_initial.py
django_json_schema_model/migrations/__init__.py
django_json_schema_model-0.1.0.dist-info/LICENSE
django_json_schema_model-0.1.0.dist-info/METADATA
django_json_schema_model-0.1.0.dist-info/WHEEL
django_json_schema_model-0.1.0.dist-info/top_level.txt
django_json_schema_model-0.1.0.dist-info/RECORD
