Metadata-Version: 2.2
Name: django-json-schema-model
Version: 0.1.0
Summary: JSON schema model for django.
Author-email: Maykin Media <support@maykinmedia.nl>
License: Copyright 2025 Maykin Media
Project-URL: Homepage, https://github.com/maykinmedia/django-json-schema-model
Project-URL: Bug Tracker, https://github.com/maykinmedia/django-json-schema-model/issues
Project-URL: Source Code, https://github.com/maykinmedia/django-json-schema-model
Keywords: django,json schema
Classifier: Development Status :: 3 - Alpha
Classifier: Framework :: Django
Classifier: Framework :: Django :: 4.2
Classifier: Intended Audience :: Developers
Classifier: Operating System :: Unix
Classifier: Operating System :: MacOS
Classifier: Operating System :: Microsoft :: Windows
Classifier: Programming Language :: Python :: 3.10
Classifier: Programming Language :: Python :: 3.11
Classifier: Programming Language :: Python :: 3.12
Classifier: Topic :: Software Development :: Libraries :: Python Modules
Requires-Python: >=3.10
License-File: LICENSE
Requires-Dist: django>=4.2
Requires-Dist: jsonschema>=4.23
Provides-Extra: tests
Requires-Dist: pytest; extra == "tests"
Requires-Dist: pytest-django; extra == "tests"
Requires-Dist: pytest-cov; extra == "tests"
Requires-Dist: tox; extra == "tests"
Requires-Dist: isort; extra == "tests"
Requires-Dist: black; extra == "tests"
Requires-Dist: flake8; extra == "tests"
Provides-Extra: docs
Requires-Dist: sphinx; extra == "docs"
Requires-Dist: sphinx-rtd-theme; extra == "docs"
Provides-Extra: release
Requires-Dist: bump-my-version; extra == "release"
